file_recoverer/__init__.py
file_recoverer/file_recoverer.py
file_recoverer/models/__init__.py
file_recoverer/models/recoverable.py
trch_file_recoverer-0.2.0.dist-info/LICENSE
trch_file_recoverer-0.2.0.dist-info/METADATA
trch_file_recoverer-0.2.0.dist-info/WHEEL
trch_file_recoverer-0.2.0.dist-info/entry_points.txt
trch_file_recoverer-0.2.0.dist-info/top_level.txt
trch_file_recoverer-0.2.0.dist-info/RECORD
