Metadata-Version: 2.1
Name: trch-file-recoverer
Version: 0.2.0
License-File: LICENSE
